{
  "generated_at": "2026-07-20T00:46:22.552140",
  "tags": {
    "F_pbr_no_r3r4": {
      "all_gates_pass": true,
      "n_closed_periods": 20,
      "endpoint_mdd_gross": -0.30726359046775065,
      "daily_mdd_gross": -0.5334951296179056,
      "G_NAV_3": true,
      "net": {
        "daily_mdd": -0.5421645777603025,
        "mdd_peak_date": "2018-05-31",
        "mdd_trough_date": "2020-03-19",
        "daily_vol_ann": 0.22768521941534559,
        "daily_sharpe": 0.6328683924404651,
        "worst_month_return": -0.16442481617376592,
        "worst_month": "2018-06",
        "cvar_5pct_1m": -0.1376908075424145,
        "cvar_1m_k": 6,
        "cvar_1m_fallback": false,
        "cvar_5pct_3m": -0.15558270738162036,
        "cvar_3m_k": 5,
        "n_days": 2452,
        "n_months": 121
      },
      "gross_mdd_peak": "2018-05-31",
      "gross_mdd_trough": "2020-03-19",
      "tracking_error_kospi": 0.1712425154626626,
      "tracking_error_kosdaq": 0.18841046417333984
    },
    "F_pbr_r6": {
      "all_gates_pass": true,
      "n_closed_periods": 20,
      "endpoint_mdd_gross": -0.34480195691242965,
      "daily_mdd_gross": -0.5623893180532025,
      "G_NAV_3": true,
      "net": {
        "daily_mdd": -0.5706686729564959,
        "mdd_peak_date": "2018-05-31",
        "mdd_trough_date": "2020-03-19",
        "daily_vol_ann": 0.22830145179753003,
        "daily_sharpe": 0.5742530565640427,
        "worst_month_return": -0.1596932437889521,
        "worst_month": "2022-09",
        "cvar_5pct_1m": -0.13908652729356977,
        "cvar_1m_k": 6,
        "cvar_1m_fallback": false,
        "cvar_5pct_3m": -0.16051444105012455,
        "cvar_3m_k": 5,
        "n_days": 2452,
        "n_months": 121
      },
      "gross_mdd_peak": "2018-05-31",
      "gross_mdd_trough": "2020-03-19",
      "tracking_error_kospi": 0.1706701073022303,
      "tracking_error_kosdaq": 0.18771957902461464
    },
    "F_momentum_rim": {
      "all_gates_pass": true,
      "n_closed_periods": 20,
      "endpoint_mdd_gross": -0.3327770012817104,
      "daily_mdd_gross": -0.559078289648993,
      "G_NAV_3": true,
      "net": {
        "daily_mdd": -0.5671242206038065,
        "mdd_peak_date": "2018-05-31",
        "mdd_trough_date": "2020-03-19",
        "daily_vol_ann": 0.2430276553155489,
        "daily_sharpe": 0.5096534331797281,
        "worst_month_return": -0.18305247042672523,
        "worst_month": "2018-06",
        "cvar_5pct_1m": -0.15780500658488067,
        "cvar_1m_k": 6,
        "cvar_1m_fallback": false,
        "cvar_5pct_3m": -0.1593973890401017,
        "cvar_3m_k": 5,
        "n_days": 2452,
        "n_months": 121
      },
      "gross_mdd_peak": "2018-05-31",
      "gross_mdd_trough": "2020-03-19",
      "tracking_error_kospi": 0.19011725556145476,
      "tracking_error_kosdaq": 0.19919786160038117
    },
    "D_pbr_only": {
      "all_gates_pass": true,
      "n_closed_periods": 20,
      "endpoint_mdd_gross": -0.35462694536792727,
      "daily_mdd_gross": -0.5595412054300195,
      "G_NAV_3": true,
      "net": {
        "daily_mdd": -0.5640189824389905,
        "mdd_peak_date": "2018-05-15",
        "mdd_trough_date": "2020-03-19",
        "daily_vol_ann": 0.2149681342837436,
        "daily_sharpe": 0.4594454236662922,
        "worst_month_return": -0.16088388968585166,
        "worst_month": "2018-10",
        "cvar_5pct_1m": -0.12455516223269757,
        "cvar_1m_k": 6,
        "cvar_1m_fallback": false,
        "cvar_5pct_3m": -0.16008399852292934,
        "cvar_3m_k": 5,
        "n_days": 2452,
        "n_months": 121
      },
      "gross_mdd_peak": "2018-05-15",
      "gross_mdd_trough": "2020-03-19",
      "tracking_error_kospi": 0.15586056549300126,
      "tracking_error_kosdaq": 0.18297050941777623
    },
    "F_no_stability_clean": {
      "all_gates_pass": true,
      "n_closed_periods": 20,
      "endpoint_mdd_gross": -0.3227329798811157,
      "daily_mdd_gross": -0.5188758747078401,
      "G_NAV_3": true,
      "net": {
        "daily_mdd": -0.5283014312688437,
        "mdd_peak_date": "2018-05-15",
        "mdd_trough_date": "2020-03-19",
        "daily_vol_ann": 0.24189459713954156,
        "daily_sharpe": 0.5538725871713562,
        "worst_month_return": -0.1797339581822166,
        "worst_month": "2018-06",
        "cvar_5pct_1m": -0.15625807323642701,
        "cvar_1m_k": 6,
        "cvar_1m_fallback": false,
        "cvar_5pct_3m": -0.17121108211224545,
        "cvar_3m_k": 5,
        "n_days": 2452,
        "n_months": 121
      },
      "gross_mdd_peak": "2018-05-15",
      "gross_mdd_trough": "2020-03-19",
      "tracking_error_kospi": 0.19305062893994687,
      "tracking_error_kosdaq": 0.20825873045482932
    },
    "U_pbr_path_ew": {
      "all_gates_pass": true,
      "n_closed_periods": 20,
      "endpoint_mdd_gross": -0.30472293177304444,
      "daily_mdd_gross": -0.5148648140881639,
      "G_NAV_3": true,
      "net": {
        "daily_mdd": -0.5225085398704993,
        "mdd_peak_date": "2018-06-07",
        "mdd_trough_date": "2020-03-19",
        "daily_vol_ann": 0.2159406869561073,
        "daily_sharpe": 0.29467156059959493,
        "worst_month_return": -0.1852708740066521,
        "worst_month": "2018-10",
        "cvar_5pct_1m": -0.1378422361828716,
        "cvar_1m_k": 6,
        "cvar_1m_fallback": false,
        "cvar_5pct_3m": -0.17633074810309798,
        "cvar_3m_k": 5,
        "n_days": 2452,
        "n_months": 121
      },
      "gross_mdd_peak": "2018-06-07",
      "gross_mdd_trough": "2020-03-19",
      "tracking_error_kospi": 0.13141499528402123,
      "tracking_error_kosdaq": 0.10288893976745689
    },
    "D_pbr_no_r3r4": {
      "all_gates_pass": true,
      "n_closed_periods": 20,
      "endpoint_mdd_gross": -0.37479948056886003,
      "daily_mdd_gross": -0.5618104558402026,
      "G_NAV_3": true,
      "net": {
        "daily_mdd": -0.5668566517062156,
        "mdd_peak_date": "2018-05-15",
        "mdd_trough_date": "2020-03-19",
        "daily_vol_ann": 0.2165074712228512,
        "daily_sharpe": 0.4576054721750781,
        "worst_month_return": -0.14308797320290134,
        "worst_month": "2022-09",
        "cvar_5pct_1m": -0.12991395881841705,
        "cvar_1m_k": 6,
        "cvar_1m_fallback": false,
        "cvar_5pct_3m": -0.16917204433923325,
        "cvar_3m_k": 5,
        "n_days": 2452,
        "n_months": 121
      },
      "gross_mdd_peak": "2018-05-15",
      "gross_mdd_trough": "2020-03-19",
      "tracking_error_kospi": 0.15523858807708277,
      "tracking_error_kosdaq": 0.18065841719714432
    },
    "F_pbr_no_r3r4_parent": {
      "all_gates_pass": true,
      "n_closed_periods": 20,
      "endpoint_mdd_gross": -0.30078055374039125,
      "daily_mdd_gross": -0.49274519524274096,
      "G_NAV_3": true,
      "net": {
        "daily_mdd": -0.501490310093881,
        "mdd_peak_date": "2018-05-31",
        "mdd_trough_date": "2020-03-19",
        "daily_vol_ann": 0.22415239389006078,
        "daily_sharpe": 0.6294314104488931,
        "worst_month_return": -0.1823908893816133,
        "worst_month": "2018-06",
        "cvar_5pct_1m": -0.14938562159539193,
        "cvar_1m_k": 6,
        "cvar_1m_fallback": false,
        "cvar_5pct_3m": -0.17044154901473188,
        "cvar_3m_k": 5,
        "n_days": 2452,
        "n_months": 121
      },
      "gross_mdd_peak": "2018-05-31",
      "gross_mdd_trough": "2020-03-19",
      "tracking_error_kospi": 0.17779155966218455,
      "tracking_error_kosdaq": 0.19592801242018967
    }
  }
}